rovr/__init__.py
rovr/__main__.py
rovr/action_buttons/__init__.py
rovr/action_buttons/copy_button.py
rovr/action_buttons/cut_button.py
rovr/action_buttons/delete_button.py
rovr/action_buttons/new_item_button.py
rovr/action_buttons/paste_button.py
rovr/action_buttons/rename_item_button.py
rovr/action_buttons/sort_order.py
rovr/action_buttons/unzip_button.py
rovr/action_buttons/zip_button.py
rovr/app.py
rovr/classes/__init__.py
rovr/classes/archive.py
rovr/classes/exceptions.py
rovr/classes/mixins.py
rovr/classes/session_manager.py
rovr/classes/textual_options.py
rovr/classes/textual_validators.py
rovr/classes/theme.py
rovr/components/__init__.py
rovr/components/popup_option_list.py
rovr/components/search_container.py
rovr/components/special_option_list.py
rovr/config/config.toml
rovr/config/keybinds/sane.toml
rovr/config/keybinds/vim.toml
rovr/config/migration.json
rovr/config/pins.json
rovr/config/schema.json
rovr/core/__init__.py
rovr/core/file_list.py
rovr/core/file_list_container.py
rovr/core/pinned_sidebar.py
rovr/core/preview_container.py
rovr/first_launch.py
rovr/first_launch.tcss
rovr/footer/__init__.py
rovr/footer/clipboard_container.py
rovr/footer/metadata_container.py
rovr/footer/process_container.py
rovr/functions/__init__.py
rovr/functions/config.py
rovr/functions/folder_prefs.py
rovr/functions/icons.py
rovr/functions/path.py
rovr/functions/pins.py
rovr/functions/system_clipboard.py
rovr/functions/themes.py
rovr/functions/utils.py
rovr/header/__init__.py
rovr/header/header.py
rovr/header/tabs.py
rovr/monkey_patches/magic_data.json
rovr/monkey_patches/puremagic_patch.py
rovr/navigation_widgets/__init__.py
rovr/navigation_widgets/buttons.py
rovr/navigation_widgets/path_input.py
rovr/py.typed
rovr/screens/__init__.py
rovr/screens/__main__.py
rovr/screens/archive_creator.py
rovr/screens/common_file_name_do_what.py
rovr/screens/delete_files.py
rovr/screens/dismissable.py
rovr/screens/fd_search.py
rovr/screens/file_in_use.py
rovr/screens/input.py
rovr-0.7.0.dist-info/licenses/LICENSE
rovr-0.7.0.dist-info/WHEEL
rovr-0.7.0.dist-info/entry_points.txt
rovr-0.7.0.dist-info/METADATA
rovr-0.7.0.dist-info/RECORD
