Metadata-Version: 2.4
Name: rovr
Version: 0.7.0
Summary: A post-modern terminal file explorer
Keywords: filemanager,fs,python,textual,tui
Author: NSPC911
License-Expression: MIT
License-File: LICENSE
Classifier: Development Status :: 4 - Beta
Classifier: License :: OSI Approved :: MIT License
Classifier: Programming Language :: Python :: 3.13
Classifier: Topic :: Desktop Environment :: File Managers
Classifier: Topic :: Utilities
Requires-Dist: backports-zstd>=1.2.0 ; python_full_version < '3.14'
Requires-Dist: fastjsonschema>=2.21.2
Requires-Dist: humanize>=4.14.0
Requires-Dist: natsort>=8.4.0
Requires-Dist: pathvalidate>=3.3.1
Requires-Dist: pdf2image>=1.17.0
Requires-Dist: pillow>=12.0.0
Requires-Dist: platformdirs>=4.5.0
Requires-Dist: psutil>=7.1.0
Requires-Dist: puremagic==1.30
Requires-Dist: rarfile>=4.2
Requires-Dist: rich>=14.3.1
Requires-Dist: rich-click>=1.9.3
Requires-Dist: send2trash>=1.8.3
Requires-Dist: textual~=7.0
Requires-Dist: textual-autocomplete>=4.0.6
Requires-Dist: textual-image[textual]>=0.8.4
Requires-Dist: textual-speedups>=0.2.1
Requires-Dist: tomli>=2.3.0
Requires-Dist: ujson>=5.11.0
Requires-Python: >=3.12, <3.14
Project-URL: Issues, https://github.com/NSPC911/rovr/issues
Project-URL: Source, https://github.com/NSPC911/rovr
Project-URL: Documentation, https://nspc911.github.io/rovr
